test_module_ravalsahil1311/BasicArithmetic.py
test_module_ravalsahil1311/__init__.py
test_module_ravalsahil1311-0.0.6.dist-info/licenses/LICENSE
test_module_ravalsahil1311-0.0.6.dist-info/METADATA
test_module_ravalsahil1311-0.0.6.dist-info/WHEEL
test_module_ravalsahil1311-0.0.6.dist-info/top_level.txt
test_module_ravalsahil1311-0.0.6.dist-info/RECORD
