Metadata-Version: 2.4
Name: test_module_ravalsahil1311
Version: 0.0.6
Summary: A small example package
Author-email: Raval Sahil <ravalsahil1311@gmail.com>, Raval Sahil-AtQor <sahil.raval@atqor.com>
License-Expression: MIT
Project-URL: Homepage, https://github.com/AzureEase/TestModule
Project-URL: Issues, https://github.com/AzureEase/TestModule/issues
Classifier: Programming Language :: Python :: 3
Classifier: Operating System :: OS Independent
Requires-Python: >=3.8
License-File: LICENSE
Dynamic: license-file
